{
  "metadataConfiguration": {
    "changeDataCaptureAttribute": "CHANGE_DATA_INDICATOR",
    "recordSourceAttribute": "RECORD_SOURCE_INDICATOR",
    "loadDateTimeAttribute": "INSCRIPTION_TIMESTAMP",
    "expiryDateTimeAttribute": "INSCRIPTION_END_TIMESTAMP",
    "eventDateTimeAttribute": "SOURCE_TIMESTAMP",
    "recordChecksumAttribute": "CHECKSUM",
    "etlProcessAttribute": "AUDIT_TRAIL_ID",
    "sourceRowIdAttribute": "INSCRIPTION_RECORD_ID"
  },
  "generationSpecificMetadata": {
    "selectedDataObject": {
      "name": "SAT_CUSTOMER_DERIVED",
      "dataObjectConnection": {
        "dataConnectionString": "Integration",
        "extensions": [
          {
            "key": "database",
            "value": "200_Integration_Layer",
            "description": "database name"
          },
          {
            "key": "schema",
            "value": "dbo",
            "description": "schema name"
          }
        ]
      },
      "dataObjectClassifications": [
        {
          "classification": "Context"
        }
      ]
    }
  },
  "dataObjectMappings": [
    {
      "mappingName": "SAT_CUSTOMER_DERIVED",
      "mappingClassifications": [
        {
          "classification": "Context"
        }
      ],
      "sourceDataObjects": [
        {
          "name": "vw_CUSTOMER_DERIVED",
          "dataObjectConnection": {
            "dataConnectionString": "Derived",
            "extensions": [
              {
                "key": "database",
                "value": "200_Integration_Layer",
                "description": "database name"
              },
              {
                "key": "schema",
                "value": "bdv",
                "description": "schema name"
              }
            ]
          },
          "dataObjectClassifications": [
            {
              "classification": "Source"
            }
          ]
        }
      ],
      "targetDataObject": {
        "name": "SAT_CUSTOMER_DERIVED",
        "dataObjectConnection": {
          "dataConnectionString": "Integration",
          "extensions": [
            {
              "key": "database",
              "value": "200_Integration_Layer",
              "description": "database name"
            },
            {
              "key": "schema",
              "value": "dbo",
              "description": "schema name"
            }
          ]
        },
        "dataObjectClassifications": [
          {
            "classification": "Context"
          }
        ]
      },
      "relatedDataObjects": [
        {
          "name": "HUB_CUSTOMER",
          "dataObjectConnection": {
            "dataConnectionString": "Integration",
            "extensions": [
              {
                "key": "database",
                "value": "200_Integration_Layer",
                "description": "database name"
              },
              {
                "key": "schema",
                "value": "dbo",
                "description": "schema name"
              }
            ]
          },
          "dataObjectClassifications": [
            {
              "classification": "CoreBusinessConcept"
            }
          ]
        }
      ],
      "dataItemMappings": [
        {
          "sourceDataItems": [
            {
              "name": "REFERRAL_OFFER_CLEAN",
              "dataType": "varchar",
              "characterLength": 7,
              "ordinalPosition": 6
            }
          ],
          "targetDataItem": {
            "name": "REFERRAL_OFFER_CLEAN",
            "dataType": "nvarchar",
            "characterLength": 100,
            "ordinalPosition": 7
          }
        }
      ],
      "businessKeys": [
        {
          "businessKeyComponentMapping": [
            {
              "sourceDataItems": [
                {
                  "name": "CUSTOMER_ID",
                  "isHardCodedValue": false
                }
              ],
              "targetDataItem": {
                "name": "CUSTOMER_ID"
              }
            }
          ],
          "surrogateKey": "CUSTOMER_SK"
        }
      ],
      "filterCriterion": "",
      "enabled": true
    }
  ]
}